simple_mail/__init__.py
simple_mail/admin.py
simple_mail/apps.py
simple_mail/fields.py
simple_mail/forms.py
simple_mail/mailer.py
simple_mail/models.py
simple_mail/tests.py
simple_mail/translation.py
simple_mail/views.py
simple_mail/widgets.py
simple_mail/management/__init__.py
simple_mail/management/commands/__init__.py
simple_mail/management/commands/register_mails.py
simple_mail/management/commands/unregister_mails.py
simple_mail/migrations/0001_initial.py
simple_mail/migrations/__init__.py
simple_mail/templates/admin/simple_mail/simplemail/change_form.html
simple_mail/templates/admin/simple_mail/simplemail/context.html
simple_mail/templates/admin/simple_mail/simplemail/send_test_mail.html
simple_mail/templates/simple_mail/default.html
django_simple_mail-2.3.5.dist-info/LICENSE
django_simple_mail-2.3.5.dist-info/METADATA
django_simple_mail-2.3.5.dist-info/WHEEL
django_simple_mail-2.3.5.dist-info/top_level.txt
django_simple_mail-2.3.5.dist-info/RECORD
