Metadata-Version: 2.1
Name: django-simple-mail
Version: 2.3.5
Summary: A simple and customizable email template built for Django
Home-page: https://github.com/charlesthk/django-simple-mail
Author: Charles TISSIER
Author-email: charles@vingtcinq.io
License: MIT
Keywords: python django mail html template
Classifier: Development Status :: 5 - Production/Stable
Classifier: Intended Audience :: Developers
Classifier: Topic :: Software Development :: Libraries :: Python Modules
Classifier: License :: OSI Approved :: MIT License
Classifier: Framework :: Django :: 3.0
Classifier: Framework :: Django :: 2.2
Classifier: Framework :: Django :: 2.1
Classifier: Framework :: Django :: 2.0
Classifier: Framework :: Django :: 1.11
Classifier: Framework :: Django :: 1.10
Classifier: Framework :: Django :: 1.9
Classifier: Programming Language :: Python :: 3
Classifier: Programming Language :: Python :: 3.2
Classifier: Programming Language :: Python :: 3.3
Classifier: Programming Language :: Python :: 3.4
Classifier: Programming Language :: Python :: 3.5
Classifier: Programming Language :: Python :: 3.6
License-File: LICENSE
Requires-Dist: html2text (>=2018.1.9)
Requires-Dist: premailer (>=3.2.0)
Requires-Dist: Pillow (>=5.2.0)
Requires-Dist: django-imagekit (>=4.0.2)
